{
    "packageName": "Backup Battery Automation",
    "author": "Michael Pierce",
    "version": "3.0.0",
    "minimumHEVersion": "2.2.8",
    "licenseFile": "https://raw.githubusercontent.com/mikee385/hubitat-mikee385/master/LICENSE",
    "releaseNotes": "Add shutdown when battery charge is low and add Device Monitor",
    "dateReleased": "2023-01-28",
    "apps": [
        {
            "id": "3773bced-1945-464b-ab83-95aa5f752708",
            "name": "Backup Battery Automation",
            "namespace": "mikee385",
            "location": "https://raw.githubusercontent.com/mikee385/hubitat-mikee385/master/apps/backup-battery-automation.groovy",
            "required": true,
            "oauth": false,
            "primary": true
        }
    ]
}