{
    "packageName": "Bathroom Fan Automation",
    "author": "Michael Pierce",
    "version": "6.2.1",
    "minimumHEVersion": "2.2.8",
    "licenseFile": "https://raw.githubusercontent.com/mikee385/hubitat-mikee385/master/LICENSE",
    "releaseNotes": "Fix issue where sensor values are integers instead of decimals",
    "dateReleased": "2022-09-15",
    "apps": [
        {
            "id": "47b33df5-abb1-4296-903a-71bebc4c2565",
            "name": "Bathroom Fan Automation",
            "namespace": "mikee385",
            "location": "https://raw.githubusercontent.com/mikee385/hubitat-mikee385/master/apps/bathroom-fan-automation.groovy",
            "required": true,
            "oauth": false,
            "primary": true
        }
    ]
}