{
    "packageName": "Dog Alerts",
    "author": "Michael Pierce",
    "version": "1.3.1",
    "minimumHEVersion": "1.0.0",
    "licenseFile": "https://raw.githubusercontent.com/mikee385/hubitat-mikee385/master/LICENSE",
    "releaseNotes": "Fix calls to inaccessible methods",
    "dateReleased": "2021-06-05",
    "apps": [
        {
            "id": "0b123dd1-8526-4d9c-a301-ce44b12b5b03",
            "name": "Dog Alerts",
            "namespace": "mikee385",
            "location": "https://raw.githubusercontent.com/mikee385/hubitat-mikee385/master/apps/dog-alerts.groovy",
            "required": true,
            "oauth": false,
            "primary": true
        }
    ]
}