{
    "packageName": "Window Alerts",
    "author": "Michael Pierce",
    "version": "1.0.1",
    "minimumHEVersion": "1.0.0",
    "licenseFile": "https://raw.githubusercontent.com/mikee385/hubitat-mikee385/master/LICENSE",
    "releaseNotes": "Fix incorrect use of unsubscribe for unschedule",
    "dateReleased": "2021-01-15",
    "apps": [
        {
            "id": "5513b8d1-02cd-4af9-b20c-7fab56c2742d",
            "name": "Window Alerts",
            "namespace": "mikee385",
            "location": "https://raw.githubusercontent.com/mikee385/hubitat-mikee385/master/apps/window-alerts.groovy",
            "required": true,
            "oauth": false,
            "primary": true
        }
    ]
}